sample/sample.v
module counter( clock, count );
  input   clock;
  output  [3:0] count;

  reg     [3:0] internal_counter;
  initial internal_counter = 4'b0;

  assign count = internal_counter;

  always @ (posedge clock)
  begin
    internal_counter <= internal_counter + 1;
  end
 
endmodule

sample/sample_ut.v
`timescale 1ns/1ns
`include "sample.v"

module sample_ut;
reg clock;
wire [3:0] count;

counter counter_under_test( .clock(clock), .count(count) );

initial begin
    clock = 0;
    forever #5 clock = ~clock;
end

initial begin
#200 $finish;
end

initial begin
$dumpfile("sample_ut.vcd");
$dumpvars(0, sample_ut);
$display("Test complete");
end
endmodule

sample/sample_ut.vcd
$date
	Sun Sep  3 17:42:38 2023
$end
$version
	Icarus Verilog
$end
$timescale
	1ns
$end
$scope module sample_ut $end
$var wire 4 ! count [3:0] $end
$var reg 1 " clock $end
$scope module counter_under_test $end
$var wire 1 " clock $end
$var wire 4 # count [3:0] $end
$var reg 4 $ internal_counter [3:0] $end
$upscope $end
$upscope $end
$enddefinitions $end
$comment Show the parameter values. $end
$dumpall
$end
#0
$dumpvars
b0 $
b0 #
0"
b0 !
$end
#5
b1 !
b1 #
b1 $
1"
#10
0"
#15
b10 !
b10 #
b10 $
1"
#20
0"
#25
b11 !
b11 #
b11 $
1"
#30
0"
#35
b100 !
b100 #
b100 $
1"
#40
0"
#45
b101 !
b101 #
b101 $
1"
#50
0"
#55
b110 !
b110 #
b110 $
1"
#60
0"
#65
b111 !
b111 #
b111 $
1"
#70
0"
#75
b1000 !
b1000 #
b1000 $
1"
#80
0"
#85
b1001 !
b1001 #
b1001 $
1"
#90
0"
#95
b1010 !
b1010 #
b1010 $
1"
#100
0"
#105
b1011 !
b1011 #
b1011 $
1"
#110
0"
#115
b1100 !
b1100 #
b1100 $
1"
#120
0"
#125
b1101 !
b1101 #
b1101 $
1"
#130
0"
#135
b1110 !
b1110 #
b1110 $
1"
#140
0"
#145
b1111 !
b1111 #
b1111 $
1"
#150
0"
#155
b0 !
b0 #
b0 $
1"
#160
0"
#165
b1 !
b1 #
b1 $
1"
#170
0"
#175
b10 !
b10 #
b10 $
1"
#180
0"
#185
b11 !
b11 #
b11 $
1"
#190
0"
#195
b100 !
b100 #
b100 $
1"
